{"nodes": [{"id": "knowledge_admin", "label": "knowledge_admin.py", "file_type": "code", "source_file": "brain/api/knowledge/knowledge_admin.py", "source_location": "L1"}, {"id": "knowledge_admin_list_knowledge_base_directories", "label": "list_knowledge_base_directories()", "file_type": "code", "source_file": "brain/api/knowledge/knowledge_admin.py", "source_location": "L30"}, {"id": "knowledge_admin_list_knowledge_base_documents", "label": "list_knowledge_base_documents()", "file_type": "code", "source_file": "brain/api/knowledge/knowledge_admin.py", "source_location": "L41"}, {"id": "knowledge_admin_list_workspace_documents", "label": "list_workspace_documents()", "file_type": "code", "source_file": "brain/api/knowledge/knowledge_admin.py", "source_location": "L47"}, {"id": "knowledge_admin_read_workspace_document", "label": "read_workspace_document()", "file_type": "code", "source_file": "brain/api/knowledge/knowledge_admin.py", "source_location": "L54"}, {"id": "knowledge_admin_save_workspace_document", "label": "save_workspace_document()", "file_type": "code", "source_file": "brain/api/knowledge/knowledge_admin.py", "source_location": "L63"}, {"id": "knowledge_admin_save_uploaded_document", "label": "save_uploaded_document()", "file_type": "code", "source_file": "brain/api/knowledge/knowledge_admin.py", "source_location": "L72"}, {"id": "knowledge_admin_save_uploaded_artifact", "label": "save_uploaded_artifact()", "file_type": "code", "source_file": "brain/api/knowledge/knowledge_admin.py", "source_location": "L92"}, {"id": "knowledge_admin_save_workspace_note", "label": "save_workspace_note()", "file_type": "code", "source_file": "brain/api/knowledge/knowledge_admin.py", "source_location": "L120"}, {"id": "knowledge_admin_create_workspace_directory", "label": "create_workspace_directory()", "file_type": "code", "source_file": "brain/api/knowledge/knowledge_admin.py", "source_location": "L146"}, {"id": "knowledge_admin_delete_workspace_directory", "label": "delete_workspace_directory()", "file_type": "code", "source_file": "brain/api/knowledge/knowledge_admin.py", "source_location": "L162"}, {"id": "knowledge_admin_delete_workspace_document", "label": "delete_workspace_document()", "file_type": "code", "source_file": "brain/api/knowledge/knowledge_admin.py", "source_location": "L185"}, {"id": "knowledge_admin_move_workspace_document", "label": "move_workspace_document()", "file_type": "code", "source_file": "brain/api/knowledge/knowledge_admin.py", "source_location": "L194"}, {"id": "knowledge_admin_update_workspace_document_meta", "label": "update_workspace_document_meta()", "file_type": "code", "source_file": "brain/api/knowledge/knowledge_admin.py", "source_location": "L211"}, {"id": "knowledge_admin_build_document_summary", "label": "_build_document_summary()", "file_type": "code", "source_file": "brain/api/knowledge/knowledge_admin.py", "source_location": "L236"}, {"id": "knowledge_admin_rationale_1", "label": "Workspace document management for the admin console.", "file_type": "rationale", "source_file": "brain/api/knowledge/knowledge_admin.py", "source_location": "L1"}, {"id": "knowledge_admin_rationale_31", "label": "Return all subdirectory paths under knowledge/, relative to workspace root.", "file_type": "rationale", "source_file": "brain/api/knowledge/knowledge_admin.py", "source_location": "L31"}, {"id": "knowledge_admin_rationale_42", "label": "Return documents under the workspace knowledge/ directory.", "file_type": "rationale", "source_file": "brain/api/knowledge/knowledge_admin.py", "source_location": "L42"}, {"id": "knowledge_admin_rationale_48", "label": "Return editable documents under the workspace.", "file_type": "rationale", "source_file": "brain/api/knowledge/knowledge_admin.py", "source_location": "L48"}, {"id": "knowledge_admin_rationale_55", "label": "Read a document from the workspace.", "file_type": "rationale", "source_file": "brain/api/knowledge/knowledge_admin.py", "source_location": "L55"}, {"id": "knowledge_admin_rationale_64", "label": "Create or overwrite a text document in the workspace.", "file_type": "rationale", "source_file": "brain/api/knowledge/knowledge_admin.py", "source_location": "L64"}, {"id": "knowledge_admin_rationale_78", "label": "Save an uploaded file into the workspace root.", "file_type": "rationale", "source_file": "brain/api/knowledge/knowledge_admin.py", "source_location": "L78"}, {"id": "knowledge_admin_rationale_98", "label": "Save a binary artifact into the workspace without indexing it.", "file_type": "rationale", "source_file": "brain/api/knowledge/knowledge_admin.py", "source_location": "L98"}, {"id": "knowledge_admin_rationale_121", "label": "Create a manual note under knowledge/notes.", "file_type": "rationale", "source_file": "brain/api/knowledge/knowledge_admin.py", "source_location": "L121"}, {"id": "knowledge_admin_rationale_147", "label": "Create a directory under the workspace root.", "file_type": "rationale", "source_file": "brain/api/knowledge/knowledge_admin.py", "source_location": "L147"}, {"id": "knowledge_admin_rationale_163", "label": "Delete a directory under the workspace root. Must be empty.", "file_type": "rationale", "source_file": "brain/api/knowledge/knowledge_admin.py", "source_location": "L163"}, {"id": "knowledge_admin_rationale_186", "label": "Delete a document from the workspace.", "file_type": "rationale", "source_file": "brain/api/knowledge/knowledge_admin.py", "source_location": "L186"}, {"id": "knowledge_admin_rationale_195", "label": "Rename or relocate a document within the workspace.", "file_type": "rationale", "source_file": "brain/api/knowledge/knowledge_admin.py", "source_location": "L195"}, {"id": "knowledge_admin_rationale_219", "label": "Update persisted metadata for a workspace document.", "file_type": "rationale", "source_file": "brain/api/knowledge/knowledge_admin.py", "source_location": "L219"}], "edges": [{"source": "knowledge_admin", "target": "datetime", "relation": "imports_from", "confidence": "EXTRACTED", "source_file": "brain/api/knowledge/knowledge_admin.py", "source_location": "L5", "weight": 1.0}, {"source": "knowledge_admin", "target": "pathlib", "relation": "imports_from", "confidence": "EXTRACTED", "source_file": "brain/api/knowledge/knowledge_admin.py", "source_location": "L6", "weight": 1.0}, {"source": "knowledge_admin", "target": "typing", "relation": "imports_from", "confidence": "EXTRACTED", "source_file": "brain/api/knowledge/knowledge_admin.py", "source_location": "L7", "weight": 1.0}, {"source": "knowledge_admin", "target": "knowledge_indexer", "relation": "imports_from", "confidence": "EXTRACTED", "source_file": "brain/api/knowledge/knowledge_admin.py", "source_location": "L9", "weight": 1.0}, {"source": "knowledge_admin", "target": "knowledge_doc_meta", "relation": "imports_from", "confidence": "EXTRACTED", "source_file": "brain/api/knowledge/knowledge_admin.py", "source_location": "L10", "weight": 1.0}, {"source": "knowledge_admin", "target": "knowledge_workspace", "relation": "imports_from", "confidence": "EXTRACTED", "source_file": "brain/api/knowledge/knowledge_admin.py", "source_location": "L17", "weight": 1.0}, {"source": "knowledge_admin", "target": "personas_personas", "relation": "imports_from", "confidence": "EXTRACTED", "source_file": "brain/api/knowledge/knowledge_admin.py", "source_location": "L27", "weight": 1.0}, {"source": "knowledge_admin", "target": "knowledge_admin_list_knowledge_base_directories", "relation": "contains", "confidence": "EXTRACTED", "source_file": "brain/api/knowledge/knowledge_admin.py", "source_location": "L30", "weight": 1.0}, {"source": "knowledge_admin", "target": "knowledge_admin_list_knowledge_base_documents", "relation": "contains", "confidence": "EXTRACTED", "source_file": "brain/api/knowledge/knowledge_admin.py", "source_location": "L41", "weight": 1.0}, {"source": "knowledge_admin", "target": "knowledge_admin_list_workspace_documents", "relation": "contains", "confidence": "EXTRACTED", "source_file": "brain/api/knowledge/knowledge_admin.py", "source_location": "L47", "weight": 1.0}, {"source": "knowledge_admin", "target": "knowledge_admin_read_workspace_document", "relation": "contains", "confidence": "EXTRACTED", "source_file": "brain/api/knowledge/knowledge_admin.py", "source_location": "L54", "weight": 1.0}, {"source": "knowledge_admin", "target": "knowledge_admin_save_workspace_document", "relation": "contains", "confidence": "EXTRACTED", "source_file": "brain/api/knowledge/knowledge_admin.py", "source_location": "L63", "weight": 1.0}, {"source": "knowledge_admin", "target": "knowledge_admin_save_uploaded_document", "relation": "contains", "confidence": "EXTRACTED", "source_file": "brain/api/knowledge/knowledge_admin.py", "source_location": "L72", "weight": 1.0}, {"source": "knowledge_admin", "target": "knowledge_admin_save_uploaded_artifact", "relation": "contains", "confidence": "EXTRACTED", "source_file": "brain/api/knowledge/knowledge_admin.py", "source_location": "L92", "weight": 1.0}, {"source": "knowledge_admin", "target": "knowledge_admin_save_workspace_note", "relation": "contains", "confidence": "EXTRACTED", "source_file": "brain/api/knowledge/knowledge_admin.py", "source_location": "L120", "weight": 1.0}, {"source": "knowledge_admin", "target": "knowledge_admin_create_workspace_directory", "relation": "contains", "confidence": "EXTRACTED", "source_file": "brain/api/knowledge/knowledge_admin.py", "source_location": "L146", "weight": 1.0}, {"source": "knowledge_admin", "target": "knowledge_admin_delete_workspace_directory", "relation": "contains", "confidence": "EXTRACTED", "source_file": "brain/api/knowledge/knowledge_admin.py", "source_location": "L162", "weight": 1.0}, {"source": "knowledge_admin", "target": "knowledge_admin_delete_workspace_document", "relation": "contains", "confidence": "EXTRACTED", "source_file": "brain/api/knowledge/knowledge_admin.py", "source_location": "L185", "weight": 1.0}, {"source": "knowledge_admin", "target": "knowledge_admin_move_workspace_document", "relation": "contains", "confidence": "EXTRACTED", "source_file": "brain/api/knowledge/knowledge_admin.py", "source_location": "L194", "weight": 1.0}, {"source": "knowledge_admin", "target": "knowledge_admin_update_workspace_document_meta", "relation": "contains", "confidence": "EXTRACTED", "source_file": "brain/api/knowledge/knowledge_admin.py", "source_location": "L211", "weight": 1.0}, {"source": "knowledge_admin", "target": "knowledge_admin_build_document_summary", "relation": "contains", "confidence": "EXTRACTED", "source_file": "brain/api/knowledge/knowledge_admin.py", "source_location": "L236", "weight": 1.0}, {"source": "knowledge_admin_list_knowledge_base_documents", "target": "knowledge_admin_build_document_summary", "relation": "calls", "confidence": "INFERRED", "source_file": "brain/api/knowledge/knowledge_admin.py", "source_location": "L44", "weight": 0.8}, {"source": "knowledge_admin_list_workspace_documents", "target": "knowledge_admin_build_document_summary", "relation": "calls", "confidence": "INFERRED", "source_file": "brain/api/knowledge/knowledge_admin.py", "source_location": "L51", "weight": 0.8}, {"source": "knowledge_admin_read_workspace_document", "target": "knowledge_admin_build_document_summary", "relation": "calls", "confidence": "INFERRED", "source_file": "brain/api/knowledge/knowledge_admin.py", "source_location": "L58", "weight": 0.8}, {"source": "knowledge_admin_save_workspace_document", "target": "knowledge_admin_build_document_summary", "relation": "calls", "confidence": "INFERRED", "source_file": "brain/api/knowledge/knowledge_admin.py", "source_location": "L69", "weight": 0.8}, {"source": "knowledge_admin_save_uploaded_document", "target": "knowledge_admin_build_document_summary", "relation": "calls", "confidence": "INFERRED", "source_file": "brain/api/knowledge/knowledge_admin.py", "source_location": "L89", "weight": 0.8}, {"source": "knowledge_admin_save_workspace_note", "target": "knowledge_admin_build_document_summary", "relation": "calls", "confidence": "INFERRED", "source_file": "brain/api/knowledge/knowledge_admin.py", "source_location": "L143", "weight": 0.8}, {"source": "knowledge_admin_move_workspace_document", "target": "knowledge_admin_build_document_summary", "relation": "calls", "confidence": "INFERRED", "source_file": "brain/api/knowledge/knowledge_admin.py", "source_location": "L201", "weight": 0.8}, {"source": "knowledge_admin_update_workspace_document_meta", "target": "knowledge_admin_build_document_summary", "relation": "calls", "confidence": "INFERRED", "source_file": "brain/api/knowledge/knowledge_admin.py", "source_location": "L233", "weight": 0.8}, {"source": "knowledge_admin_rationale_1", "target": "knowledge_admin", "relation": "rationale_for", "confidence": "EXTRACTED", "source_file": "brain/api/knowledge/knowledge_admin.py", "source_location": "L1", "weight": 1.0}, {"source": "knowledge_admin_rationale_31", "target": "knowledge_admin_list_knowledge_base_directories", "relation": "rationale_for", "confidence": "EXTRACTED", "source_file": "brain/api/knowledge/knowledge_admin.py", "source_location": "L31", "weight": 1.0}, {"source": "knowledge_admin_rationale_42", "target": "knowledge_admin_list_knowledge_base_documents", "relation": "rationale_for", "confidence": "EXTRACTED", "source_file": "brain/api/knowledge/knowledge_admin.py", "source_location": "L42", "weight": 1.0}, {"source": "knowledge_admin_rationale_48", "target": "knowledge_admin_list_workspace_documents", "relation": "rationale_for", "confidence": "EXTRACTED", "source_file": "brain/api/knowledge/knowledge_admin.py", "source_location": "L48", "weight": 1.0}, {"source": "knowledge_admin_rationale_55", "target": "knowledge_admin_read_workspace_document", "relation": "rationale_for", "confidence": "EXTRACTED", "source_file": "brain/api/knowledge/knowledge_admin.py", "source_location": "L55", "weight": 1.0}, {"source": "knowledge_admin_rationale_64", "target": "knowledge_admin_save_workspace_document", "relation": "rationale_for", "confidence": "EXTRACTED", "source_file": "brain/api/knowledge/knowledge_admin.py", "source_location": "L64", "weight": 1.0}, {"source": "knowledge_admin_rationale_78", "target": "knowledge_admin_save_uploaded_document", "relation": "rationale_for", "confidence": "EXTRACTED", "source_file": "brain/api/knowledge/knowledge_admin.py", "source_location": "L78", "weight": 1.0}, {"source": "knowledge_admin_rationale_98", "target": "knowledge_admin_save_uploaded_artifact", "relation": "rationale_for", "confidence": "EXTRACTED", "source_file": "brain/api/knowledge/knowledge_admin.py", "source_location": "L98", "weight": 1.0}, {"source": "knowledge_admin_rationale_121", "target": "knowledge_admin_save_workspace_note", "relation": "rationale_for", "confidence": "EXTRACTED", "source_file": "brain/api/knowledge/knowledge_admin.py", "source_location": "L121", "weight": 1.0}, {"source": "knowledge_admin_rationale_147", "target": "knowledge_admin_create_workspace_directory", "relation": "rationale_for", "confidence": "EXTRACTED", "source_file": "brain/api/knowledge/knowledge_admin.py", "source_location": "L147", "weight": 1.0}, {"source": "knowledge_admin_rationale_163", "target": "knowledge_admin_delete_workspace_directory", "relation": "rationale_for", "confidence": "EXTRACTED", "source_file": "brain/api/knowledge/knowledge_admin.py", "source_location": "L163", "weight": 1.0}, {"source": "knowledge_admin_rationale_186", "target": "knowledge_admin_delete_workspace_document", "relation": "rationale_for", "confidence": "EXTRACTED", "source_file": "brain/api/knowledge/knowledge_admin.py", "source_location": "L186", "weight": 1.0}, {"source": "knowledge_admin_rationale_195", "target": "knowledge_admin_move_workspace_document", "relation": "rationale_for", "confidence": "EXTRACTED", "source_file": "brain/api/knowledge/knowledge_admin.py", "source_location": "L195", "weight": 1.0}, {"source": "knowledge_admin_rationale_219", "target": "knowledge_admin_update_workspace_document_meta", "relation": "rationale_for", "confidence": "EXTRACTED", "source_file": "brain/api/knowledge/knowledge_admin.py", "source_location": "L219", "weight": 1.0}]}