{"nodes": [{"id": "retrieval_service", "label": "retrieval_service.py", "file_type": "code", "source_file": "brain/api/core/retrieval_service.py", "source_location": "L1"}, {"id": "retrieval_service_retrievalbundle", "label": "RetrievalBundle", "file_type": "code", "source_file": "brain/api/core/retrieval_service.py", "source_location": "L20"}, {"id": "retrieval_service_retrieve_context", "label": "retrieve_context()", "file_type": "code", "source_file": "brain/api/core/retrieval_service.py", "source_location": "L28"}, {"id": "retrieval_service_safe_search", "label": "_safe_search()", "file_type": "code", "source_file": "brain/api/core/retrieval_service.py", "source_location": "L107"}, {"id": "retrieval_service_rerank_by_distance", "label": "_rerank_by_distance()", "file_type": "code", "source_file": "brain/api/core/retrieval_service.py", "source_location": "L129"}, {"id": "retrieval_service_days_since", "label": "_days_since()", "file_type": "code", "source_file": "brain/api/core/retrieval_service.py", "source_location": "L167"}, {"id": "retrieval_service_record_importance", "label": "_record_importance()", "file_type": "code", "source_file": "brain/api/core/retrieval_service.py", "source_location": "L179"}, {"id": "retrieval_service_build_diagnostics", "label": "_build_diagnostics()", "file_type": "code", "source_file": "brain/api/core/retrieval_service.py", "source_location": "L188"}, {"id": "retrieval_service_rationale_1", "label": "Unified retrieval and reranking service for brain context.", "file_type": "rationale", "source_file": "brain/api/core/retrieval_service.py", "source_location": "L1"}, {"id": "retrieval_service_rationale_21", "label": "Immutable result bundle from retrieval + reranking.", "file_type": "rationale", "source_file": "brain/api/core/retrieval_service.py", "source_location": "L21"}, {"id": "retrieval_service_rationale_34", "label": "Retrieve and rerank context from knowledge and memory tables.      Returns a Ret", "file_type": "rationale", "source_file": "brain/api/core/retrieval_service.py", "source_location": "L34"}, {"id": "retrieval_service_rationale_117", "label": "Search with error handling \u2014 return empty on failure.", "file_type": "rationale", "source_file": "brain/api/core/retrieval_service.py", "source_location": "L117"}, {"id": "retrieval_service_rationale_136", "label": "Sort candidates by effective distance (ascending).      effective_distance = raw", "file_type": "rationale", "source_file": "brain/api/core/retrieval_service.py", "source_location": "L136"}, {"id": "retrieval_service_rationale_168", "label": "Return the number of days between the record's date and today.", "file_type": "rationale", "source_file": "brain/api/core/retrieval_service.py", "source_location": "L168"}, {"id": "retrieval_service_rationale_180", "label": "Extract importance score from record metadata.", "file_type": "rationale", "source_file": "brain/api/core/retrieval_service.py", "source_location": "L180"}, {"id": "retrieval_service_rationale_197", "label": "Build a diagnostics dict for logging and observability.", "file_type": "rationale", "source_file": "brain/api/core/retrieval_service.py", "source_location": "L197"}], "edges": [{"source": "retrieval_service", "target": "dataclasses", "relation": "imports_from", "confidence": "EXTRACTED", "source_file": "brain/api/core/retrieval_service.py", "source_location": "L5", "weight": 1.0}, {"source": "retrieval_service", "target": "datetime", "relation": "imports_from", "confidence": "EXTRACTED", "source_file": "brain/api/core/retrieval_service.py", "source_location": "L6", "weight": 1.0}, {"source": "retrieval_service", "target": "typing", "relation": "imports_from", "confidence": "EXTRACTED", "source_file": "brain/api/core/retrieval_service.py", "source_location": "L7", "weight": 1.0}, {"source": "retrieval_service", "target": "logging", "relation": "imports", "confidence": "EXTRACTED", "source_file": "brain/api/core/retrieval_service.py", "source_location": "L8", "weight": 1.0}, {"source": "retrieval_service", "target": "config", "relation": "imports_from", "confidence": "EXTRACTED", "source_file": "brain/api/core/retrieval_service.py", "source_location": "L10", "weight": 1.0}, {"source": "retrieval_service", "target": "infra_db", "relation": "imports_from", "confidence": "EXTRACTED", "source_file": "brain/api/core/retrieval_service.py", "source_location": "L11", "weight": 1.0}, {"source": "retrieval_service", "target": "memory_embedder", "relation": "imports_from", "confidence": "EXTRACTED", "source_file": "brain/api/core/retrieval_service.py", "source_location": "L12", "weight": 1.0}, {"source": "retrieval_service", "target": "memory_retrieval", "relation": "imports_from", "confidence": "EXTRACTED", "source_file": "brain/api/core/retrieval_service.py", "source_location": "L13", "weight": 1.0}, {"source": "retrieval_service", "target": "safety_observability", "relation": "imports_from", "confidence": "EXTRACTED", "source_file": "brain/api/core/retrieval_service.py", "source_location": "L14", "weight": 1.0}, {"source": "retrieval_service", "target": "retrieval_service_retrievalbundle", "relation": "contains", "confidence": "EXTRACTED", "source_file": "brain/api/core/retrieval_service.py", "source_location": "L20", "weight": 1.0}, {"source": "retrieval_service", "target": "retrieval_service_retrieve_context", "relation": "contains", "confidence": "EXTRACTED", "source_file": "brain/api/core/retrieval_service.py", "source_location": "L28", "weight": 1.0}, {"source": "retrieval_service", "target": "retrieval_service_safe_search", "relation": "contains", "confidence": "EXTRACTED", "source_file": "brain/api/core/retrieval_service.py", "source_location": "L107", "weight": 1.0}, {"source": "retrieval_service", "target": "retrieval_service_rerank_by_distance", "relation": "contains", "confidence": "EXTRACTED", "source_file": "brain/api/core/retrieval_service.py", "source_location": "L129", "weight": 1.0}, {"source": "retrieval_service", "target": "retrieval_service_days_since", "relation": "contains", "confidence": "EXTRACTED", "source_file": "brain/api/core/retrieval_service.py", "source_location": "L167", "weight": 1.0}, {"source": "retrieval_service", "target": "retrieval_service_record_importance", "relation": "contains", "confidence": "EXTRACTED", "source_file": "brain/api/core/retrieval_service.py", "source_location": "L179", "weight": 1.0}, {"source": "retrieval_service", "target": "retrieval_service_build_diagnostics", "relation": "contains", "confidence": "EXTRACTED", "source_file": "brain/api/core/retrieval_service.py", "source_location": "L188", "weight": 1.0}, {"source": "retrieval_service_retrieve_context", "target": "retrieval_service_safe_search", "relation": "calls", "confidence": "INFERRED", "source_file": "brain/api/core/retrieval_service.py", "source_location": "L57", "weight": 0.8}, {"source": "retrieval_service_retrieve_context", "target": "retrieval_service_rerank_by_distance", "relation": "calls", "confidence": "INFERRED", "source_file": "brain/api/core/retrieval_service.py", "source_location": "L67", "weight": 0.8}, {"source": "retrieval_service_retrieve_context", "target": "retrieval_service_build_diagnostics", "relation": "calls", "confidence": "INFERRED", "source_file": "brain/api/core/retrieval_service.py", "source_location": "L89", "weight": 0.8}, {"source": "retrieval_service_retrieve_context", "target": "retrieval_service_retrievalbundle", "relation": "calls", "confidence": "INFERRED", "source_file": "brain/api/core/retrieval_service.py", "source_location": "L100", "weight": 0.8}, {"source": "retrieval_service_rerank_by_distance", "target": "retrieval_service_days_since", "relation": "calls", "confidence": "INFERRED", "source_file": "brain/api/core/retrieval_service.py", "source_location": "L154", "weight": 0.8}, {"source": "retrieval_service_rerank_by_distance", "target": "retrieval_service_record_importance", "relation": "calls", "confidence": "INFERRED", "source_file": "brain/api/core/retrieval_service.py", "source_location": "L158", "weight": 0.8}, {"source": "retrieval_service_rationale_1", "target": "retrieval_service", "relation": "rationale_for", "confidence": "EXTRACTED", "source_file": "brain/api/core/retrieval_service.py", "source_location": "L1", "weight": 1.0}, {"source": "retrieval_service_rationale_21", "target": "retrieval_service_retrievalbundle", "relation": "rationale_for", "confidence": "EXTRACTED", "source_file": "brain/api/core/retrieval_service.py", "source_location": "L21", "weight": 1.0}, {"source": "retrieval_service_rationale_34", "target": "retrieval_service_retrieve_context", "relation": "rationale_for", "confidence": "EXTRACTED", "source_file": "brain/api/core/retrieval_service.py", "source_location": "L34", "weight": 1.0}, {"source": "retrieval_service_rationale_117", "target": "retrieval_service_safe_search", "relation": "rationale_for", "confidence": "EXTRACTED", "source_file": "brain/api/core/retrieval_service.py", "source_location": "L117", "weight": 1.0}, {"source": "retrieval_service_rationale_136", "target": "retrieval_service_rerank_by_distance", "relation": "rationale_for", "confidence": "EXTRACTED", "source_file": "brain/api/core/retrieval_service.py", "source_location": "L136", "weight": 1.0}, {"source": "retrieval_service_rationale_168", "target": "retrieval_service_days_since", "relation": "rationale_for", "confidence": "EXTRACTED", "source_file": "brain/api/core/retrieval_service.py", "source_location": "L168", "weight": 1.0}, {"source": "retrieval_service_rationale_180", "target": "retrieval_service_record_importance", "relation": "rationale_for", "confidence": "EXTRACTED", "source_file": "brain/api/core/retrieval_service.py", "source_location": "L180", "weight": 1.0}, {"source": "retrieval_service_rationale_197", "target": "retrieval_service_build_diagnostics", "relation": "rationale_for", "confidence": "EXTRACTED", "source_file": "brain/api/core/retrieval_service.py", "source_location": "L197", "weight": 1.0}]}