{"nodes": [{"id": "test_identity", "label": "test_identity.py", "file_type": "code", "source_file": "brain/api/tests/test_identity.py", "source_location": "L1"}, {"id": "test_identity_workspace_tmp", "label": "workspace_tmp()", "file_type": "code", "source_file": "brain/api/tests/test_identity.py", "source_location": "L14"}, {"id": "test_identity_write_identity", "label": "_write_identity()", "file_type": "code", "source_file": "brain/api/tests/test_identity.py", "source_location": "L23"}, {"id": "test_identity_mock_paths", "label": "_mock_paths()", "file_type": "code", "source_file": "brain/api/tests/test_identity.py", "source_location": "L27"}, {"id": "test_identity_test_parse_identity_returns_defaults_when_file_missing", "label": "test_parse_identity_returns_defaults_when_file_missing()", "file_type": "code", "source_file": "brain/api/tests/test_identity.py", "source_location": "L37"}, {"id": "test_identity_test_parse_identity_extracts_fields_from_markdown", "label": "test_parse_identity_extracts_fields_from_markdown()", "file_type": "code", "source_file": "brain/api/tests/test_identity.py", "source_location": "L47"}, {"id": "test_identity_test_parse_identity_partial_fields_use_defaults", "label": "test_parse_identity_partial_fields_use_defaults()", "file_type": "code", "source_file": "brain/api/tests/test_identity.py", "source_location": "L62"}, {"id": "test_identity_test_parse_identity_persona_override", "label": "test_parse_identity_persona_override()", "file_type": "code", "source_file": "brain/api/tests/test_identity.py", "source_location": "L78"}, {"id": "test_identity_test_parse_identity_ignores_unknown_keys", "label": "test_parse_identity_ignores_unknown_keys()", "file_type": "code", "source_file": "brain/api/tests/test_identity.py", "source_location": "L97"}, {"id": "test_identity_rationale_1", "label": "Tests for parse_identity() in knowledge.workspace.", "file_type": "rationale", "source_file": "brain/api/tests/test_identity.py", "source_location": "L1"}, {"id": "test_identity_rationale_15", "label": "Create a minimal workspace with IDENTITY.md.", "file_type": "rationale", "source_file": "brain/api/tests/test_identity.py", "source_location": "L15"}, {"id": "test_identity_rationale_28", "label": "Return a dict matching resolve_core_document_paths output.", "file_type": "rationale", "source_file": "brain/api/tests/test_identity.py", "source_location": "L28"}, {"id": "test_identity_rationale_79", "label": "When persona has its own IDENTITY.md, parse_identity returns overridden values.", "file_type": "rationale", "source_file": "brain/api/tests/test_identity.py", "source_location": "L79"}], "edges": [{"source": "test_identity", "target": "pathlib", "relation": "imports_from", "confidence": "EXTRACTED", "source_file": "brain/api/tests/test_identity.py", "source_location": "L5", "weight": 1.0}, {"source": "test_identity", "target": "unittest_mock", "relation": "imports_from", "confidence": "EXTRACTED", "source_file": "brain/api/tests/test_identity.py", "source_location": "L6", "weight": 1.0}, {"source": "test_identity", "target": "pytest", "relation": "imports", "confidence": "EXTRACTED", "source_file": "brain/api/tests/test_identity.py", "source_location": "L8", "weight": 1.0}, {"source": "test_identity", "target": "knowledge_workspace", "relation": "imports_from", "confidence": "EXTRACTED", "source_file": "brain/api/tests/test_identity.py", "source_location": "L10", "weight": 1.0}, {"source": "test_identity", "target": "test_identity_workspace_tmp", "relation": "contains", "confidence": "EXTRACTED", "source_file": "brain/api/tests/test_identity.py", "source_location": "L14", "weight": 1.0}, {"source": "test_identity", "target": "test_identity_write_identity", "relation": "contains", "confidence": "EXTRACTED", "source_file": "brain/api/tests/test_identity.py", "source_location": "L23", "weight": 1.0}, {"source": "test_identity", "target": "test_identity_mock_paths", "relation": "contains", "confidence": "EXTRACTED", "source_file": "brain/api/tests/test_identity.py", "source_location": "L27", "weight": 1.0}, {"source": "test_identity", "target": "test_identity_test_parse_identity_returns_defaults_when_file_missing", "relation": "contains", "confidence": "EXTRACTED", "source_file": "brain/api/tests/test_identity.py", "source_location": "L37", "weight": 1.0}, {"source": "test_identity", "target": "test_identity_test_parse_identity_extracts_fields_from_markdown", "relation": "contains", "confidence": "EXTRACTED", "source_file": "brain/api/tests/test_identity.py", "source_location": "L47", "weight": 1.0}, {"source": "test_identity", "target": "test_identity_test_parse_identity_partial_fields_use_defaults", "relation": "contains", "confidence": "EXTRACTED", "source_file": "brain/api/tests/test_identity.py", "source_location": "L62", "weight": 1.0}, {"source": "test_identity", "target": "test_identity_test_parse_identity_persona_override", "relation": "contains", "confidence": "EXTRACTED", "source_file": "brain/api/tests/test_identity.py", "source_location": "L78", "weight": 1.0}, {"source": "test_identity", "target": "test_identity_test_parse_identity_ignores_unknown_keys", "relation": "contains", "confidence": "EXTRACTED", "source_file": "brain/api/tests/test_identity.py", "source_location": "L97", "weight": 1.0}, {"source": "test_identity_test_parse_identity_extracts_fields_from_markdown", "target": "test_identity_write_identity", "relation": "calls", "confidence": "INFERRED", "source_file": "brain/api/tests/test_identity.py", "source_location": "L48", "weight": 0.8}, {"source": "test_identity_test_parse_identity_extracts_fields_from_markdown", "target": "test_identity_mock_paths", "relation": "calls", "confidence": "INFERRED", "source_file": "brain/api/tests/test_identity.py", "source_location": "L55", "weight": 0.8}, {"source": "test_identity_test_parse_identity_partial_fields_use_defaults", "target": "test_identity_write_identity", "relation": "calls", "confidence": "INFERRED", "source_file": "brain/api/tests/test_identity.py", "source_location": "L63", "weight": 0.8}, {"source": "test_identity_test_parse_identity_partial_fields_use_defaults", "target": "test_identity_mock_paths", "relation": "calls", "confidence": "INFERRED", "source_file": "brain/api/tests/test_identity.py", "source_location": "L70", "weight": 0.8}, {"source": "test_identity_test_parse_identity_ignores_unknown_keys", "target": "test_identity_write_identity", "relation": "calls", "confidence": "INFERRED", "source_file": "brain/api/tests/test_identity.py", "source_location": "L98", "weight": 0.8}, {"source": "test_identity_test_parse_identity_ignores_unknown_keys", "target": "test_identity_mock_paths", "relation": "calls", "confidence": "INFERRED", "source_file": "brain/api/tests/test_identity.py", "source_location": "L105", "weight": 0.8}, {"source": "test_identity_rationale_1", "target": "test_identity", "relation": "rationale_for", "confidence": "EXTRACTED", "source_file": "brain/api/tests/test_identity.py", "source_location": "L1", "weight": 1.0}, {"source": "test_identity_rationale_15", "target": "test_identity_workspace_tmp", "relation": "rationale_for", "confidence": "EXTRACTED", "source_file": "brain/api/tests/test_identity.py", "source_location": "L15", "weight": 1.0}, {"source": "test_identity_rationale_28", "target": "test_identity_mock_paths", "relation": "rationale_for", "confidence": "EXTRACTED", "source_file": "brain/api/tests/test_identity.py", "source_location": "L28", "weight": 1.0}, {"source": "test_identity_rationale_79", "target": "test_identity_test_parse_identity_persona_override", "relation": "rationale_for", "confidence": "EXTRACTED", "source_file": "brain/api/tests/test_identity.py", "source_location": "L79", "weight": 1.0}]}